mobipick_gui/__init__.py
mobipick_gui/__main__.py
mobipick_gui/ansi.py
mobipick_gui/cli.py
mobipick_gui/config.py
mobipick_gui/log_widget.py
mobipick_gui/main_window.py
mobipick_gui/process_tab.py
mobipick_gui/resources/__init__.py
mobipick_gui/resources/clean.bash
mobipick_gui/resources/docker-compose.yml
mobipick_gui/resources/config/docker_cp_image_tag.yaml
mobipick_gui/resources/config/gui_settings.yaml
mobipick_gui/resources/config/worlds.yaml
mobipick_gui/resources/scripts/.gitkeep
mobipick_labs_docker_gui-0.1.0.dist-info/METADATA
mobipick_labs_docker_gui-0.1.0.dist-info/WHEEL
mobipick_labs_docker_gui-0.1.0.dist-info/entry_points.txt
mobipick_labs_docker_gui-0.1.0.dist-info/top_level.txt
mobipick_labs_docker_gui-0.1.0.dist-info/RECORD
