Metadata-Version: 2.4
Name: mobipick-labs-docker-gui
Version: 0.1.0
Summary: PyQt5 desktop controller for the Mobipick Labs Docker simulation
Author: Mobipick Labs
License: Proprietary
Project-URL: Homepage, https://github.com/openai/mobipick_labs_docker_gui
Keywords: mobipick,docker,gui,ros,simulation
Classifier: Development Status :: 4 - Beta
Classifier: Intended Audience :: Developers
Classifier: License :: Other/Proprietary License
Classifier: Programming Language :: Python
Classifier: Programming Language :: Python :: 3
Classifier: Programming Language :: Python :: 3 :: Only
Classifier: Programming Language :: Python :: 3.8
Classifier: Programming Language :: Python :: 3.9
Classifier: Programming Language :: Python :: 3.10
Classifier: Programming Language :: Python :: 3.11
Classifier: Operating System :: POSIX :: Linux
Classifier: Topic :: Software Development :: User Interfaces
Requires-Python: >=3.8
Requires-Dist: PyQt5>=5.15
Requires-Dist: PyYAML>=6.0
Requires-Dist: importlib-resources>=5.0; python_version < "3.9"
